django_queryable_properties-1.12.1.dist-info/licenses/AUTHORS.rst
django_queryable_properties-1.12.1.dist-info/licenses/LICENSE
queryable_properties/__init__.py
queryable_properties/compat.py
queryable_properties/exceptions.py
queryable_properties/managers.py
queryable_properties/query.py
queryable_properties/admin/__init__.py
queryable_properties/admin/checks.py
queryable_properties/admin/filters.py
queryable_properties/properties/__init__.py
queryable_properties/properties/annotation.py
queryable_properties/properties/base.py
queryable_properties/properties/cache_behavior.py
queryable_properties/properties/contrib.py
queryable_properties/properties/inheritance.py
queryable_properties/properties/mixins.py
queryable_properties/properties/operations.py
queryable_properties/properties/specialized.py
queryable_properties/properties/subquery.py
queryable_properties/utils/__init__.py
queryable_properties/utils/deprecation.py
queryable_properties/utils/internal.py
tests/__init__.py
tests/conftest.py
tests/marks.py
tests/settings.py
tests/test_compat.py
tests/test_managers.py
tests/test_query.py
tests/app_management/__init__.py
tests/app_management/admin.py
tests/app_management/models.py
tests/dummy_lib/__init__.py
tests/dummy_lib/models.py
tests/inheritance/__init__.py
tests/inheritance/models.py
tests/test_admin/__init__.py
tests/test_admin/conftest.py
tests/test_admin/test_admin.py
tests/test_admin/test_checks.py
tests/test_admin/test_filters.py
tests/test_properties/__init__.py
tests/test_properties/test_annotation.py
tests/test_properties/test_base.py
tests/test_properties/test_contrib.py
tests/test_properties/test_inheritance.py
tests/test_properties/test_mixins.py
tests/test_properties/test_operations.py
tests/test_properties/test_specialized.py
tests/test_properties/test_subquery.py
tests/test_queries/__init__.py
tests/test_queries/test_annotations.py
tests/test_queries/test_async.py
tests/test_queries/test_exceptions.py
tests/test_queries/test_filters.py
tests/test_queries/test_non_model_instance.py
tests/test_queries/test_ordering.py
tests/test_queries/test_updates.py
django_queryable_properties-1.12.1.dist-info/METADATA
django_queryable_properties-1.12.1.dist-info/WHEEL
django_queryable_properties-1.12.1.dist-info/top_level.txt
django_queryable_properties-1.12.1.dist-info/RECORD
